galaxest/__init__.py
galaxest/adb.py
galaxest/args_parser.py
galaxest/automation.py
galaxest/config.py
galaxest/device.py
galaxest/main.py
galaxest/parallel.py
galaxest/runner.py
galaxest/setup.py
galaxest/automations/__init__.py
galaxest/automations/katalon.py
galaxest/devices/__init__.py
galaxest/devices/stf.py
galaxest/labs/__init__.py
galaxest/labs/stf.py
galaxest/locale/__init__.py
galaxest/locale/en.py
galaxest-0.0.8.dist-info/LICENSE
galaxest-0.0.8.dist-info/METADATA
galaxest-0.0.8.dist-info/WHEEL
galaxest-0.0.8.dist-info/entry_points.txt
galaxest-0.0.8.dist-info/top_level.txt
galaxest-0.0.8.dist-info/RECORD
